polars_api_compat/__init__.py
polars_api_compat/containers.py
polars_api_compat/translate.py
polars_api_compat/utils.py
polars_api_compat/pandas_like/__init__.py
polars_api_compat/pandas_like/column_object.py
polars_api_compat/pandas_like/dataframe_object.py
polars_api_compat/pandas_like/expr.py
polars_api_compat/pandas_like/group_by_object.py
polars_api_compat/spec/__init__.py
polars_api_compat-0.1.4.dist-info/METADATA
polars_api_compat-0.1.4.dist-info/WHEEL
polars_api_compat-0.1.4.dist-info/licenses/LICENSE.md
polars_api_compat-0.1.4.dist-info/RECORD
