Metadata-Version: 2.1
Name: polars_api_compat
Version: 0.1.4
Summary: Extremely lightweight compatibility layer between pandas, Polars, and cuDF
Project-URL: Homepage, https://github.com/MarcoGorelli/polars-api-compat
Project-URL: Bug Tracker, https://github.com/MarcoGorelli/polars-api-compat
Author-email: Marco Gorelli <33491632+MarcoGorelli@users.noreply.github.com>
License-File: LICENSE.md
Classifier: License :: OSI Approved :: MIT License
Classifier: Operating System :: OS Independent
Classifier: Programming Language :: Python :: 3
Requires-Python: >=3.8
Requires-Dist: packaging; python_version < '3.9'
